hdl/ripple_carry_adder_4bit.v
`timescale 1ns/1ps
`default_nettype none

module full_adder(
  input  wire a,
  input  wire b,
  input  wire cin,
  output wire sum,
  output wire cout
);
  assign sum  = a ^ b ^ cin;
  assign cout = (a & b) | (cin & (a ^ b));
endmodule

module ripple_carry_adder_4bit(
  input  wire [3:0] A,
  input  wire [3:0] B,
  input  wire       Cin,
  output wire [3:0] Sum,
  output wire       Cout
);
  wire c1, c2, c3;

  full_adder fa0(.a(A[0]), .b(B[0]), .cin(Cin), .sum(Sum[0]), .cout(c1));
  full_adder fa1(.a(A[1]), .b(B[1]), .cin(c1 ), .sum(Sum[1]), .cout(c2));
  full_adder fa2(.a(A[2]), .b(B[2]), .cin(c2 ), .sum(Sum[2]), .cout(c3));
  full_adder fa3(.a(A[3]), .b(B[3]), .cin(c3 ), .sum(Sum[3]), .cout(Cout));
endmodule

`default_nettype wire

hdl/tb_ripple_carry_adder_4bit.v
`timescale 1ns/1ps

module tb_ripple_carry_adder_4bit;
    reg  [3:0] A;
    reg  [3:0] B;
    reg        Cin;
    wire [3:0] Sum;
    wire       Cout;
    integer    i, j;
    reg  [4:0] expected;

    // DUT
    ripple_carry_adder_4bit DUT (.A(A), .B(B), .Cin(Cin), .Sum(Sum), .Cout(Cout));

    initial begin
        // VCD (ouvre-le depuis hdl/)
        $dumpfile("rca.vcd");
        $dumpvars(0, tb_ripple_carry_adder_4bit);

        $display("  A   B  Cin | Cout  Sum  (= expected)");

        // init stable visible
        A=0; B=0; Cin=0; #10;

        // balaye TOUTES les combinaisons 16x16, Cin=0 puis Cin=1
        for (i = 0; i < 16; i = i + 1) begin
            for (j = 0; j < 16; j = j + 1) begin
                A = i; B = j; Cin = 0; #10;
                expected = i + j + 0;
                if ({Cout,Sum} !== expected) begin
                    $display("ERR: A=%0d B=%0d Cin=0 -> {%b,%b} != %0d", A,B,Cout,Sum,expected);
                    $fatal(1);
                end else begin
                    $display("%2d + %2d + 0 -> {%0d,%b} = %2d", A,B,Cout,Sum,expected);
                end

                A = i; B = j; Cin = 1; #10;
                expected = i + j + 1;
                if ({Cout,Sum} !== expected) begin
                    $display("ERR: A=%0d B=%0d Cin=1 -> {%b,%b} != %0d", A,B,Cout,Sum,expected);
                    $fatal(1);
                end else begin
                    $display("%2d + %2d + 1 -> {%0d,%b} = %2d", A,B,Cout,Sum,expected);
                end
            end
        end

        $display("All test cases passed ✅");
        $finish;
    end
endmodule

hdl/rca.vcd
$date
	Thu Aug 28 15:11:36 2025
$end
$version
	Icarus Verilog
$end
$timescale
	1ps
$end
$scope module tb_ripple_carry_adder_4bit $end
$var wire 4 ! Sum [3:0] $end
$var wire 1 " Cout $end
$var reg 4 # A [3:0] $end
$var reg 4 $ B [3:0] $end
$var reg 1 % Cin $end
$var reg 5 & expected [4:0] $end
$var integer 32 ' i [31:0] $end
$var integer 32 ( j [31:0] $end
$scope module DUT $end
$var wire 4 ) A [3:0] $end
$var wire 4 * B [3:0] $end
$var wire 1 % Cin $end
$var wire 1 + c3 $end
$var wire 1 , c2 $end
$var wire 1 - c1 $end
$var wire 4 . Sum [3:0] $end
$var wire 1 " Cout $end
$scope module fa0 $end
$var wire 1 / a $end
$var wire 1 0 b $end
$var wire 1 % cin $end
$var wire 1 - cout $end
$var wire 1 1 sum $end
$upscope $end
$scope module fa1 $end
$var wire 1 2 a $end
$var wire 1 3 b $end
$var wire 1 - cin $end
$var wire 1 , cout $end
$var wire 1 4 sum $end
$upscope $end
$scope module fa2 $end
$var wire 1 5 a $end
$var wire 1 6 b $end
$var wire 1 , cin $end
$var wire 1 + cout $end
$var wire 1 7 sum $end
$upscope $end
$scope module fa3 $end
$var wire 1 8 a $end
$var wire 1 9 b $end
$var wire 1 + cin $end
$var wire 1 " cout $end
$var wire 1 : sum $end
$upscope $end
$upscope $end
$upscope $end
$enddefinitions $end
#0
$dumpvars
0:
09
08
07
06
05
04
03
02
01
00
0/
b0 .
0-
0,
0+
b0 *
b0 )
bx (
bx '
bx &
0%
b0 $
b0 #
0"
b0 !
$end
#10000
b0 (
b0 '
#20000
b1 !
b1 .
11
1%
b0 &
#30000
b1 !
b1 .
11
10
0%
b1 $
b1 *
b1 (
b1 &
#40000
14
1-
b10 !
b10 .
01
1%
#50000
0-
b10 !
b10 .
01
00
13
0%
b10 $
b10 *
b10 (
b10 &
#60000
b11 !
b11 .
11
1%
#70000
b11 !
b11 .
11
10
0%
b11 $
b11 *
b11 (
b11 &
#80000
17
1,
04
1-
b100 !
b100 .
01
1%
#90000
0:
0,
0+
17
0-
b100 !
b100 .
01
00
03
16
0%
b100 $
b100 *
b100 (
b100 &
#100000
b101 !
b101 .
11
1%
#110000
b101 !
b101 .
11
10
0%
b101 $
b101 *
b101 (
b101 &
#120000
14
1-
b110 !
b110 .
01
1%
#130000
0-
b110 !
b110 .
01
00
13
0%
b110 $
b110 *
b110 (
b110 &
#140000
b111 !
b111 .
11
1%
#150000
b111 !
b111 .
11
10
0%
b111 $
b111 *
b111 (
b111 &
#160000
1:
1+
07
1,
04
1-
b1000 !
b1000 .
01
1%
#170000
0,
0+
0"
07
1:
0-
b1000 !
b1000 .
01
00
03
06
19
0%
b1000 $
b1000 *
b1000 (
b1000 &
#180000
b1001 !
b1001 .
11
1%
#190000
b1001 !
b1001 .
11
10
0%
b1001 $
b1001 *
b1001 (
b1001 &
#200000
14
1-
b1010 !
b1010 .
01
1%
#210000
0-
b1010 !
b1010 .
01
00
13
0%
b1010 $
b1010 *
b1010 (
b1010 &
#220000
b1011 !
b1011 .
11
1%
#230000
b1011 !
b1011 .
11
10
0%
b1011 $
b1011 *
b1011 (
b1011 &
#240000
17
1,
04
1-
b1100 !
b1100 .
01
1%
#250000
0"
1:
0,
0+
17
0-
b1100 !
b1100 .
01
00
03
16
0%
b1100 $
b1100 *
b1100 (
b1100 &
#260000
b1101 !
b1101 .
11
1%
#270000
b1101 !
b1101 .
11
10
0%
b1101 $
b1101 *
b1101 (
b1101 &
#280000
14
1-
b1110 !
b1110 .
01
1%
#290000
0-
b1110 !
b1110 .
01
00
13
0%
b1110 $
b1110 *
b1110 (
b1110 &
#300000
b1111 !
b1111 .
11
1%
#310000
b1111 !
b1111 .
11
10
0%
b1111 $
b1111 *
b1111 (
b1111 &
#320000
1"
0:
1+
07
1,
04
1-
b0 !
b0 .
01
1%
#330000
0,
0+
0"
07
0:
0-
b1 !
b1 .
11
00
03
06
09
1/
0%
b0 $
b0 *
b1 #
b1 )
b1 '
b0 (
b10000 &
#340000
14
1-
b10 !
b10 .
01
1%
b1 &
#350000
b10 !
b10 .
01
10
0%
b1 $
b1 *
b1 (
b10 &
#360000
b11 !
b11 .
11
1%
#370000
07
0,
0-
14
b11 !
b11 .
11
00
13
0%
b10 $
b10 *
b10 (
b11 &
#380000
17
1,
04
1-
b100 !
b100 .
01
1%
#390000
b100 !
b100 .
01
10
0%
b11 $
b11 *
b11 (
b100 &
#400000
b101 !
b101 .
11
1%
#410000
0:
0,
0+
0-
04
17
b101 !
b101 .
11
00
03
16
0%
b100 $
b100 *
b100 (
b101 &
#420000
14
1-
b110 !
b110 .
01
1%
#430000
b110 !
b110 .
01
10
0%
b101 $
b101 *
b101 (
b110 &
#440000
b111 !
b111 .
11
1%
#450000
0:
0+
17
0,
0-
14
b111 !
b111 .
11
00
13
0%
b110 $
b110 *
b110 (
b111 &
#460000
1:
1+
07
1,
04
1-
b1000 !
b1000 .
01
1%
#470000
b1000 !
b1000 .
01
10
0%
b111 $
b111 *
b111 (
b1000 &
#480000
b1001 !
b1001 .
11
1%
#490000
0,
0+
0"
0-
04
07
1:
b1001 !
b1001 .
11
00
03
06
19
0%
b1000 $
b1000 *
b1000 (
b1001 &
#500000
14
1-
b1010 !
b1010 .
01
1%
#510000
b1010 !
b1010 .
01
10
0%
b1001 $
b1001 *
b1001 (
b1010 &
#520000
b1011 !
b1011 .
11
1%
#530000
07
0,
0-
14
b1011 !
b1011 .
11
00
13
0%
b1010 $
b1010 *
b1010 (
b1011 &
#540000
17
1,
04
1-
b1100 !
b1100 .
01
1%
#550000
b1100 !
b1100 .
01
10
0%
b1011 $
b1011 *
b1011 (
b1100 &
#560000
b1101 !
b1101 .
11
1%
#570000
0"
1:
0,
0+
0-
04
17
b1101 !
b1101 .
11
00
03
16
0%
b1100 $
b1100 *
b1100 (
b1101 &
#580000
14
1-
b1110 !
b1110 .
01
1%
#590000
b1110 !
b1110 .
01
10
0%
b1101 $
b1101 *
b1101 (
b1110 &
#600000
b1111 !
b1111 .
11
1%
#610000
0"
1:
0+
17
0,
0-
14
b1111 !
b1111 .
11
00
13
0%
b1110 $
b1110 *
b1110 (
b1111 &
#620000
1"
0:
1+
07
1,
04
1-
b0 !
b0 .
01
1%
#630000
b0 !
b0 .
01
10
0%
b1111 $
b1111 *
b1111 (
b10000 &
#640000
b1 !
b1 .
11
1%
#650000
0,
0+
0"
14
07
0:
0-
b10 !
b10 .
01
00
03
06
09
0/
12
0%
b0 $
b0 *
b10 #
b10 )
b10 '
b0 (
b10001 &
#660000
b11 !
b11 .
11
1%
b10 &
#670000
b11 !
b11 .
11
10
0%
b1 $
b1 *
b1 (
b11 &
#680000
17
1,
04
1-
b100 !
b100 .
01
1%
#690000
0-
b100 !
b100 .
01
00
13
0%
b10 $
b10 *
b10 (
b100 &
#700000
b101 !
b101 .
11
1%
#710000
b101 !
b101 .
11
10
0%
b11 $
b11 *
b11 (
b101 &
#720000
14
1-
b110 !
b110 .
01
1%
#730000
0:
0+
0,
17
0-
b110 !
b110 .
01
00
03
16
0%
b100 $
b100 *
b100 (
b110 &
#740000
b111 !
b111 .
11
1%
#750000
b111 !
b111 .
11
10
0%
b101 $
b101 *
b101 (
b111 &
#760000
1:
1+
07
1,
04
1-
b1000 !
b1000 .
01
1%
#770000
0-
b1000 !
b1000 .
01
00
13
0%
b110 $
b110 *
b110 (
b1000 &
#780000
b1001 !
b1001 .
11
1%
#790000
b1001 !
b1001 .
11
10
0%
b111 $
b111 *
b111 (
b1001 &
#800000
14
1-
b1010 !
b1010 .
01
1%
#810000
0+
0"
0,
07
1:
0-
b1010 !
b1010 .
01
00
03
06
19
0%
b1000 $
b1000 *
b1000 (
b1010 &
#820000
b1011 !
b1011 .
11
1%
#830000
b1011 !
b1011 .
11
10
0%
b1001 $
b1001 *
b1001 (
b1011 &
#840000
17
1,
04
1-
b1100 !
b1100 .
01
1%
#850000
0-
b1100 !
b1100 .
01
00
13
0%
b1010 $
b1010 *
b1010 (
b1100 &
#860000
b1101 !
b1101 .
11
1%
#870000
b1101 !
b1101 .
11
10
0%
b1011 $
b1011 *
b1011 (
b1101 &
#880000
14
1-
b1110 !
b1110 .
01
1%
#890000
0"
1:
0+
0,
17
0-
b1110 !
b1110 .
01
00
03
16
0%
b1100 $
b1100 *
b1100 (
b1110 &
#900000
b1111 !
b1111 .
11
1%
#910000
b1111 !
b1111 .
11
10
0%
b1101 $
b1101 *
b1101 (
b1111 &
#920000
1"
0:
1+
07
1,
04
1-
b0 !
b0 .
01
1%
#930000
0-
b0 !
b0 .
01
00
13
0%
b1110 $
b1110 *
b1110 (
b10000 &
#940000
b1 !
b1 .
11
1%
#950000
b1 !
b1 .
11
10
0%
b1111 $
b1111 *
b1111 (
b10001 &
#960000
14
1-
b10 !
b10 .
01
1%
#970000
0+
0"
0,
07
0:
0-
b11 !
b11 .
11
00
03
06
09
1/
0%
b0 $
b0 *
b11 #
b11 )
b11 '
b0 (
b10010 &
#980000
17
1,
04
1-
b100 !
b100 .
01
1%
b11 &
#990000
b100 !
b100 .
01
10
0%
b1 $
b1 *
b1 (
b100 &
#1000000
b101 !
b101 .
11
1%
#1010000
0-
04
b101 !
b101 .
11
00
13
0%
b10 $
b10 *
b10 (
b101 &
#1020000
14
1-
b110 !
b110 .
01
1%
#1030000
b110 !
b110 .
01
10
0%
b11 $
b11 *
b11 (
b110 &
#1040000
b111 !
b111 .
11
1%
#1050000
0,
0:
0+
0-
14
17
b111 !
b111 .
11
00
03
16
0%
b100 $
b100 *
b100 (
b111 &
#1060000
1:
1+
07
1,
04
1-
b1000 !
b1000 .
01
1%
#1070000
b1000 !
b1000 .
01
10
0%
b101 $
b101 *
b101 (
b1000 &
#1080000
b1001 !
b1001 .
11
1%
#1090000
0-
04
b1001 !
b1001 .
11
00
13
0%
b110 $
b110 *
b110 (
b1001 &
#1100000
14
1-
b1010 !
b1010 .
01
1%
#1110000
b1010 !
b1010 .
01
10
0%
b111 $
b111 *
b111 (
b1010 &
#1120000
b1011 !
b1011 .
11
1%
#1130000
0,
0+
0"
0-
14
07
1:
b1011 !
b1011 .
11
00
03
06
19
0%
b1000 $
b1000 *
b1000 (
b1011 &
#1140000
17
1,
04
1-
b1100 !
b1100 .
01
1%
#1150000
b1100 !
b1100 .
01
10
0%
b1001 $
b1001 *
b1001 (
b1100 &
#1160000
b1101 !
b1101 .
11
1%
#1170000
0-
04
b1101 !
b1101 .
11
00
13
0%
b1010 $
b1010 *
b1010 (
b1101 &
#1180000
14
1-
b1110 !
b1110 .
01
1%
#1190000
b1110 !
b1110 .
01
10
0%
b1011 $
b1011 *
b1011 (
b1110 &
#1200000
b1111 !
b1111 .
11
1%
#1210000
0"
0,
1:
0+
0-
14
17
b1111 !
b1111 .
11
00
03
16
0%
b1100 $
b1100 *
b1100 (
b1111 &
#1220000
1"
0:
1+
07
1,
04
1-
b0 !
b0 .
01
1%
#1230000
b0 !
b0 .
01
10
0%
b1101 $
b1101 *
b1101 (
b10000 &
#1240000
b1 !
b1 .
11
1%
#1250000
0-
04
b1 !
b1 .
11
00
13
0%
b1110 $
b1110 *
b1110 (
b10001 &
#1260000
14
1-
b10 !
b10 .
01
1%
#1270000
b10 !
b10 .
01
10
0%
b1111 $
b1111 *
b1111 (
b10010 &
#1280000
b11 !
b11 .
11
1%
#1290000
0+
0"
04
17
0:
0-
0,
b100 !
b100 .
01
00
03
06
09
0/
02
15
0%
b0 $
b0 *
b100 #
b100 )
b100 '
b0 (
b10011 &
#1300000
b101 !
b101 .
11
1%
b100 &
#1310000
b101 !
b101 .
11
10
0%
b1 $
b1 *
b1 (
b101 &
#1320000
14
1-
b110 !
b110 .
01
1%
#1330000
0-
b110 !
b110 .
01
00
13
0%
b10 $
b10 *
b10 (
b110 &
#1340000
b111 !
b111 .
11
1%
#1350000
b111 !
b111 .
11
10
0%
b11 $
b11 *
b11 (
b111 &
#1360000
1:
1+
07
1,
04
1-
b1000 !
b1000 .
01
1%
#1370000
0,
07
0-
b1000 !
b1000 .
01
00
03
16
0%
b100 $
b100 *
b100 (
b1000 &
#1380000
b1001 !
b1001 .
11
1%
#1390000
b1001 !
b1001 .
11
10
0%
b101 $
b101 *
b101 (
b1001 &
#1400000
14
1-
b1010 !
b1010 .
01
1%
#1410000
0-
b1010 !
b1010 .
01
00
13
0%
b110 $
b110 *
b110 (
b1010 &
#1420000
b1011 !
b1011 .
11
1%
#1430000
b1011 !
b1011 .
11
10
0%
b111 $
b111 *
b111 (
b1011 &
#1440000
17
1,
04
1-
b1100 !
b1100 .
01
1%
#1450000
0+
0,
0"
17
1:
0-
b1100 !
b1100 .
01
00
03
06
19
0%
b1000 $
b1000 *
b1000 (
b1100 &
#1460000
b1101 !
b1101 .
11
1%
#1470000
b1101 !
b1101 .
11
10
0%
b1001 $
b1001 *
b1001 (
b1101 &
#1480000
14
1-
b1110 !
b1110 .
01
1%
#1490000
0-
b1110 !
b1110 .
01
00
13
0%
b1010 $
b1010 *
b1010 (
b1110 &
#1500000
b1111 !
b1111 .
11
1%
#1510000
b1111 !
b1111 .
11
10
0%
b1011 $
b1011 *
b1011 (
b1111 &
#1520000
1"
0:
1+
07
1,
04
1-
b0 !
b0 .
01
1%
#1530000
0,
07
0-
b0 !
b0 .
01
00
03
16
0%
b1100 $
b1100 *
b1100 (
b10000 &
#1540000
b1 !
b1 .
11
1%
#1550000
b1 !
b1 .
11
10
0%
b1101 $
b1101 *
b1101 (
b10001 &
#1560000
14
1-
b10 !
b10 .
01
1%
#1570000
0-
b10 !
b10 .
01
00
13
0%
b1110 $
b1110 *
b1110 (
b10010 &
#1580000
b11 !
b11 .
11
1%
#1590000
b11 !
b11 .
11
10
0%
b1111 $
b1111 *
b1111 (
b10011 &
#1600000
17
1,
04
1-
b100 !
b100 .
01
1%
#1610000
0+
0,
0"
17
0:
0-
b101 !
b101 .
11
00
03
06
09
1/
0%
b0 $
b0 *
b101 #
b101 )
b101 '
b0 (
b10100 &
#1620000
14
1-
b110 !
b110 .
01
1%
b101 &
#1630000
b110 !
b110 .
01
10
0%
b1 $
b1 *
b1 (
b110 &
#1640000
b111 !
b111 .
11
1%
#1650000
0:
0+
17
0,
0-
14
b111 !
b111 .
11
00
13
0%
b10 $
b10 *
b10 (
b111 &
#1660000
1:
1+
07
1,
04
1-
b1000 !
b1000 .
01
1%
#1670000
b1000 !
b1000 .
01
10
0%
b11 $
b11 *
b11 (
b1000 &
#1680000
b1001 !
b1001 .
11
1%
#1690000
0,
0-
04
07
b1001 !
b1001 .
11
00
03
16
0%
b100 $
b100 *
b100 (
b1001 &
#1700000
14
1-
b1010 !
b1010 .
01
1%
#1710000
b1010 !
b1010 .
01
10
0%
b101 $
b101 *
b101 (
b1010 &
#1720000
b1011 !
b1011 .
11
1%
#1730000
07
0,
0-
14
b1011 !
b1011 .
11
00
13
0%
b110 $
b110 *
b110 (
b1011 &
#1740000
17
1,
04
1-
b1100 !
b1100 .
01
1%
#1750000
b1100 !
b1100 .
01
10
0%
b111 $
b111 *
b111 (
b1100 &
#1760000
b1101 !
b1101 .
11
1%
#1770000
0+
0,
0"
0-
04
17
1:
b1101 !
b1101 .
11
00
03
06
19
0%
b1000 $
b1000 *
b1000 (
b1101 &
#1780000
14
1-
b1110 !
b1110 .
01
1%
#1790000
b1110 !
b1110 .
01
10
0%
b1001 $
b1001 *
b1001 (
b1110 &
#1800000
b1111 !
b1111 .
11
1%
#1810000
0"
1:
0+
17
0,
0-
14
b1111 !
b1111 .
11
00
13
0%
b1010 $
b1010 *
b1010 (
b1111 &
#1820000
1"
0:
1+
07
1,
04
1-
b0 !
b0 .
01
1%
#1830000
b0 !
b0 .
01
10
0%
b1011 $
b1011 *
b1011 (
b10000 &
#1840000
b1 !
b1 .
11
1%
#1850000
0,
0-
04
07
b1 !
b1 .
11
00
03
16
0%
b1100 $
b1100 *
b1100 (
b10001 &
#1860000
14
1-
b10 !
b10 .
01
1%
#1870000
b10 !
b10 .
01
10
0%
b1101 $
b1101 *
b1101 (
b10010 &
#1880000
b11 !
b11 .
11
1%
#1890000
07
0,
0-
14
b11 !
b11 .
11
00
13
0%
b1110 $
b1110 *
b1110 (
b10011 &
#1900000
17
1,
04
1-
b100 !
b100 .
01
1%
#1910000
b100 !
b100 .
01
10
0%
b1111 $
b1111 *
b1111 (
b10100 &
#1920000
b101 !
b101 .
11
1%
#1930000
0+
0,
0"
14
17
0:
0-
b110 !
b110 .
01
00
03
06
09
0/
12
0%
b0 $
b0 *
b110 #
b110 )
b110 '
b0 (
b10101 &
#1940000
b111 !
b111 .
11
1%
b110 &
#1950000
b111 !
b111 .
11
10
0%
b1 $
b1 *
b1 (
b111 &
#1960000
1:
1+
07
1,
04
1-
b1000 !
b1000 .
01
1%
#1970000
0-
b1000 !
b1000 .
01
00
13
0%
b10 $
b10 *
b10 (
b1000 &
#1980000
b1001 !
b1001 .
11
1%
#1990000
b1001 !
b1001 .
11
10
0%
b11 $
b11 *
b11 (
b1001 &
#2000000
14
1-
b1010 !
b1010 .
01
1%
#2010000
0,
07
0-
b1010 !
b1010 .
01
00
03
16
0%
b100 $
b100 *
b100 (
b1010 &
#2020000
b1011 !
b1011 .
11
1%
#2030000
b1011 !
b1011 .
11
10
0%
b101 $
b101 *
b101 (
b1011 &
#2040000
17
1,
04
1-
b1100 !
b1100 .
01
1%
#2050000
0-
b1100 !
b1100 .
01
00
13
0%
b110 $
b110 *
b110 (
b1100 &
#2060000
b1101 !
b1101 .
11
1%
#2070000
b1101 !
b1101 .
11
10
0%
b111 $
b111 *
b111 (
b1101 &
#2080000
14
1-
b1110 !
b1110 .
01
1%
#2090000
0+
0"
0,
17
1:
0-
b1110 !
b1110 .
01
00
03
06
19
0%
b1000 $
b1000 *
b1000 (
b1110 &
#2100000
b1111 !
b1111 .
11
1%
#2110000
b1111 !
b1111 .
11
10
0%
b1001 $
b1001 *
b1001 (
b1111 &
#2120000
1"
0:
1+
07
1,
04
1-
b0 !
b0 .
01
1%
#2130000
0-
b0 !
b0 .
01
00
13
0%
b1010 $
b1010 *
b1010 (
b10000 &
#2140000
b1 !
b1 .
11
1%
#2150000
b1 !
b1 .
11
10
0%
b1011 $
b1011 *
b1011 (
b10001 &
#2160000
14
1-
b10 !
b10 .
01
1%
#2170000
0,
07
0-
b10 !
b10 .
01
00
03
16
0%
b1100 $
b1100 *
b1100 (
b10010 &
#2180000
b11 !
b11 .
11
1%
#2190000
b11 !
b11 .
11
10
0%
b1101 $
b1101 *
b1101 (
b10011 &
#2200000
17
1,
04
1-
b100 !
b100 .
01
1%
#2210000
0-
b100 !
b100 .
01
00
13
0%
b1110 $
b1110 *
b1110 (
b10100 &
#2220000
b101 !
b101 .
11
1%
#2230000
b101 !
b101 .
11
10
0%
b1111 $
b1111 *
b1111 (
b10101 &
#2240000
14
1-
b110 !
b110 .
01
1%
#2250000
0+
0"
0,
17
0:
0-
b111 !
b111 .
11
00
03
06
09
1/
0%
b0 $
b0 *
b111 #
b111 )
b111 '
b0 (
b10110 &
#2260000
1:
1+
07
1,
04
1-
b1000 !
b1000 .
01
1%
b111 &
#2270000
b1000 !
b1000 .
01
10
0%
b1 $
b1 *
b1 (
b1000 &
#2280000
b1001 !
b1001 .
11
1%
#2290000
0-
04
b1001 !
b1001 .
11
00
13
0%
b10 $
b10 *
b10 (
b1001 &
#2300000
14
1-
b1010 !
b1010 .
01
1%
#2310000
b1010 !
b1010 .
01
10
0%
b11 $
b11 *
b11 (
b1010 &
#2320000
b1011 !
b1011 .
11
1%
#2330000
0,
0-
14
07
b1011 !
b1011 .
11
00
03
16
0%
b100 $
b100 *
b100 (
b1011 &
#2340000
17
1,
04
1-
b1100 !
b1100 .
01
1%
#2350000
b1100 !
b1100 .
01
10
0%
b101 $
b101 *
b101 (
b1100 &
#2360000
b1101 !
b1101 .
11
1%
#2370000
0-
04
b1101 !
b1101 .
11
00
13
0%
b110 $
b110 *
b110 (
b1101 &
#2380000
14
1-
b1110 !
b1110 .
01
1%
#2390000
b1110 !
b1110 .
01
10
0%
b111 $
b111 *
b111 (
b1110 &
#2400000
b1111 !
b1111 .
11
1%
#2410000
0+
0,
0"
0-
14
17
1:
b1111 !
b1111 .
11
00
03
06
19
0%
b1000 $
b1000 *
b1000 (
b1111 &
#2420000
1"
0:
1+
07
1,
04
1-
b0 !
b0 .
01
1%
#2430000
b0 !
b0 .
01
10
0%
b1001 $
b1001 *
b1001 (
b10000 &
#2440000
b1 !
b1 .
11
1%
#2450000
0-
04
b1 !
b1 .
11
00
13
0%
b1010 $
b1010 *
b1010 (
b10001 &
#2460000
14
1-
b10 !
b10 .
01
1%
#2470000
b10 !
b10 .
01
10
0%
b1011 $
b1011 *
b1011 (
b10010 &
#2480000
b11 !
b11 .
11
1%
#2490000
0,
0-
14
07
b11 !
b11 .
11
00
03
16
0%
b1100 $
b1100 *
b1100 (
b10011 &
#2500000
17
1,
04
1-
b100 !
b100 .
01
1%
#2510000
b100 !
b100 .
01
10
0%
b1101 $
b1101 *
b1101 (
b10100 &
#2520000
b101 !
b101 .
11
1%
#2530000
0-
04
b101 !
b101 .
11
00
13
0%
b1110 $
b1110 *
b1110 (
b10101 &
#2540000
14
1-
b110 !
b110 .
01
1%
#2550000
b110 !
b110 .
01
10
0%
b1111 $
b1111 *
b1111 (
b10110 &
#2560000
b111 !
b111 .
11
1%
#2570000
0"
04
07
1:
0-
0,
0+
b1000 !
b1000 .
01
00
03
06
09
0/
02
05
18
0%
b0 $
b0 *
b1000 #
b1000 )
b1000 '
b0 (
b10111 &
#2580000
b1001 !
b1001 .
11
1%
b1000 &
#2590000
b1001 !
b1001 .
11
10
0%
b1 $
b1 *
b1 (
b1001 &
#2600000
14
1-
b1010 !
b1010 .
01
1%
#2610000
0-
b1010 !
b1010 .
01
00
13
0%
b10 $
b10 *
b10 (
b1010 &
#2620000
b1011 !
b1011 .
11
1%
#2630000
b1011 !
b1011 .
11
10
0%
b11 $
b11 *
b11 (
b1011 &
#2640000
17
1,
04
1-
b1100 !
b1100 .
01
1%
#2650000
0"
1:
0,
0+
17
0-
b1100 !
b1100 .
01
00
03
16
0%
b100 $
b100 *
b100 (
b1100 &
#2660000
b1101 !
b1101 .
11
1%
#2670000
b1101 !
b1101 .
11
10
0%
b101 $
b101 *
b101 (
b1101 &
#2680000
14
1-
b1110 !
b1110 .
01
1%
#2690000
0-
b1110 !
b1110 .
01
00
13
0%
b110 $
b110 *
b110 (
b1110 &
#2700000
b1111 !
b1111 .
11
1%
#2710000
b1111 !
b1111 .
11
10
0%
b111 $
b111 *
b111 (
b1111 &
#2720000
1"
0:
1+
07
1,
04
1-
b0 !
b0 .
01
1%
#2730000
0,
0+
07
0:
0-
b0 !
b0 .
01
00
03
06
19
0%
b1000 $
b1000 *
b1000 (
b10000 &
#2740000
b1 !
b1 .
11
1%
#2750000
b1 !
b1 .
11
10
0%
b1001 $
b1001 *
b1001 (
b10001 &
#2760000
14
1-
b10 !
b10 .
01
1%
#2770000
0-
b10 !
b10 .
01
00
13
0%
b1010 $
b1010 *
b1010 (
b10010 &
#2780000
b11 !
b11 .
11
1%
#2790000
b11 !
b11 .
11
10
0%
b1011 $
b1011 *
b1011 (
b10011 &
#2800000
17
1,
04
1-
b100 !
b100 .
01
1%
#2810000
0:
0,
0+
17
0-
b100 !
b100 .
01
00
03
16
0%
b1100 $
b1100 *
b1100 (
b10100 &
#2820000
b101 !
b101 .
11
1%
#2830000
b101 !
b101 .
11
10
0%
b1101 $
b1101 *
b1101 (
b10101 &
#2840000
14
1-
b110 !
b110 .
01
1%
#2850000
0-
b110 !
b110 .
01
00
13
0%
b1110 $
b1110 *
b1110 (
b10110 &
#2860000
b111 !
b111 .
11
1%
#2870000
b111 !
b111 .
11
10
0%
b1111 $
b1111 *
b1111 (
b10111 &
#2880000
1:
1+
07
1,
04
1-
b1000 !
b1000 .
01
1%
#2890000
0"
0,
0+
07
1:
0-
b1001 !
b1001 .
11
00
03
06
09
1/
0%
b0 $
b0 *
b1001 #
b1001 )
b1001 '
b0 (
b11000 &
#2900000
14
1-
b1010 !
b1010 .
01
1%
b1001 &
#2910000
b1010 !
b1010 .
01
10
0%
b1 $
b1 *
b1 (
b1010 &
#2920000
b1011 !
b1011 .
11
1%
#2930000
07
0,
0-
14
b1011 !
b1011 .
11
00
13
0%
b10 $
b10 *
b10 (
b1011 &
#2940000
17
1,
04
1-
b1100 !
b1100 .
01
1%
#2950000
b1100 !
b1100 .
01
10
0%
b11 $
b11 *
b11 (
b1100 &
#2960000
b1101 !
b1101 .
11
1%
#2970000
0"
1:
0,
0+
0-
04
17
b1101 !
b1101 .
11
00
03
16
0%
b100 $
b100 *
b100 (
b1101 &
#2980000
14
1-
b1110 !
b1110 .
01
1%
#2990000
b1110 !
b1110 .
01
10
0%
b101 $
b101 *
b101 (
b1110 &
#3000000
b1111 !
b1111 .
11
1%
#3010000
0"
1:
0+
17
0,
0-
14
b1111 !
b1111 .
11
00
13
0%
b110 $
b110 *
b110 (
b1111 &
#3020000
1"
0:
1+
07
1,
04
1-
b0 !
b0 .
01
1%
#3030000
b0 !
b0 .
01
10
0%
b111 $
b111 *
b111 (
b10000 &
#3040000
b1 !
b1 .
11
1%
#3050000
0,
0+
0-
04
07
0:
b1 !
b1 .
11
00
03
06
19
0%
b1000 $
b1000 *
b1000 (
b10001 &
#3060000
14
1-
b10 !
b10 .
01
1%
#3070000
b10 !
b10 .
01
10
0%
b1001 $
b1001 *
b1001 (
b10010 &
#3080000
b11 !
b11 .
11
1%
#3090000
07
0,
0-
14
b11 !
b11 .
11
00
13
0%
b1010 $
b1010 *
b1010 (
b10011 &
#3100000
17
1,
04
1-
b100 !
b100 .
01
1%
#3110000
b100 !
b100 .
01
10
0%
b1011 $
b1011 *
b1011 (
b10100 &
#3120000
b101 !
b101 .
11
1%
#3130000
0:
0,
0+
0-
04
17
b101 !
b101 .
11
00
03
16
0%
b1100 $
b1100 *
b1100 (
b10101 &
#3140000
14
1-
b110 !
b110 .
01
1%
#3150000
b110 !
b110 .
01
10
0%
b1101 $
b1101 *
b1101 (
b10110 &
#3160000
b111 !
b111 .
11
1%
#3170000
0:
0+
17
0,
0-
14
b111 !
b111 .
11
00
13
0%
b1110 $
b1110 *
b1110 (
b10111 &
#3180000
1:
1+
07
1,
04
1-
b1000 !
b1000 .
01
1%
#3190000
b1000 !
b1000 .
01
10
0%
b1111 $
b1111 *
b1111 (
b11000 &
#3200000
b1001 !
b1001 .
11
1%
#3210000
0"
0,
0+
14
07
1:
0-
b1010 !
b1010 .
01
00
03
06
09
0/
12
0%
b0 $
b0 *
b1010 #
b1010 )
b1010 '
b0 (
b11001 &
#3220000
b1011 !
b1011 .
11
1%
b1010 &
#3230000
b1011 !
b1011 .
11
10
0%
b1 $
b1 *
b1 (
b1011 &
#3240000
17
1,
04
1-
b1100 !
b1100 .
01
1%
#3250000
0-
b1100 !
b1100 .
01
00
13
0%
b10 $
b10 *
b10 (
b1100 &
#3260000
b1101 !
b1101 .
11
1%
#3270000
b1101 !
b1101 .
11
10
0%
b11 $
b11 *
b11 (
b1101 &
